sphinx_watch/__init__.py
sphinx_watch/cli.py
sphinx_watch/handlers.py
sphinx_watch/httpd.py
sphinx_watch-0.1.2.dist-info/entry_points.txt
sphinx_watch-0.1.2.dist-info/LICENSE
sphinx_watch-0.1.2.dist-info/WHEEL
sphinx_watch-0.1.2.dist-info/METADATA
sphinx_watch-0.1.2.dist-info/RECORD
